Workbook
Name ta共通仮設費率: #REF!
Name ta契約保証費用: #REF!
Name ta現場管理費率: #REF!
Name ta工種区分: #REF!
Name ta施工地域区分: #REF!
Name ta前払区分: #REF!

Sheet スライド調書（様式4-2号）
G2: 様式4-2号
B3: スライド調書 | E3: =IF(E16>F16,"減額スライド",IF(E16<F16,"増額スライド","")) -> 増額スライド
C5: 元設計 | D5: 出来高 | E5: 残工事 | G5: スライド額
E6: 変動前 | F6: 変動後
C7: ①
B8: 設計額（税込） | C8: =経費計算シート!C35 -> 285583100 | D8: - | E8: - | F8: - | G8: - | I8: 87.585935
C9: ② | D9: ⑤ | E9: ⑦=②-⑤ | F9: ⑧
B10: 工事価格（税抜） | C10: =経費計算シート!C30+経費計算シート!C32 -> 259621000 | D10: =経費計算シート!O33 -> 93076000 | E10: =C10-D10 -> 166545000 | F10: =経費計算シート!M33 -> 170224000 | G10: -
B12: 消費税相当額 | C12: =経費計算シート!C34 -> 25962100 | D12: - | E12: - | F12: - | G12: -
C13: ③
B14: 請負代金額（税込） | C14: =ROUNDDOWN(C8*I8/100,0) -> 250130627 | D14: - | E14: - | F14: - | G14: -
B15: 請負工事価格 | C15: ④ | D15: ⑥=⑤×（③/①） | E15: P1'=④-⑥ | F15: P2'=⑧×（③/①） | G15: =IF(E16>F16,"S'=P2'-P1'+（P1''×1/100）","S'=P2'-P1'-（P1''×1/100）") -> S'=P2'-P1'-（P1''×1/100）
B16: （請負代金額（税抜）） | C16: =ROUNDDOWN(C14*10/11,0) -> 227391479 | D16: =ROUNDDOWN(D10*C14/C8,0) -> 81521484 | E16: =C16-D16 -> 145869995 | F16: =ROUNDDOWN(F10*C14/C8,0) -> 149092281 | G16: =F16-E16-(E20*1/100) -> 1858432.9
B18: 消費税相当額 | C18: =C14-C16 -> 22739148 | D18: - | E18: - | F18: - | G18: -
B19: 請負工事価格 （新工種抜き） | C19: ⑨ （請負率考慮） | D19: ⑩ （請負率考慮） | E19: P1''=⑨-⑩
B20: （請負代金額（税抜）） | C20: =ROUNDDOWN(経費計算シート!Q33*C14/C8,0) -> 218181818 | D20: =ROUNDDOWN(経費計算シート!S33*C14/C8,0) -> 81796504 | E20: =C20-D20 -> 136385314

Sheet 経費計算シート
C2: A | E2: B | G2: C | I2: D | K2: E | M2: F | O2: G | Q2: H | S2: I
B3: スライド基準日より後の単価適用日の新工種がある場合 | C3: 変更設計書 | E3: 変更設計書 残工事 【設計書(1)】 | G3: 単価更新設計書 残工事 【設計書(2)】 | I3: 変更設計書 出来高 【Excelシート】 ※A-B（設計書無し） | K3: スライド設計書 【設計書(3)】 | M3: 単価更新設計書 残工事 【設計書(4)】 【Excel計算】 | O3: 変更設計書 出来高 【設計書(6)】 【Excel計算】 | Q3: 変更設計書 新工種抜き 【設計書(7)】 | S3: 変更設計書 新工種抜き 出来高 【設計書(9)】【Excel計算】 | U3: 出来高【設計書(5)】チェック
A4: 直接工事費 | U4: 変更設計書-残工事【設計書(1)】
B5: ①直接工事費 | C5: 159813308 | E5: 101128573 | G5: 104093462 | I5: 特殊集計 区分外 | J5: =C5-E5-J6-J7 -> 23729675 | K5: 162778197 | M5: 104093462 | O5: 58684735 | Q5: 152213308 | S5: 58684735 | U5: =C5-E5 -> 58684735 | V5: =IF(U5=O5,"OK","NG") -> OK
I6: 特殊集計 区分(水道) | J6: =C7-E7 -> 34700000
B7: ①’水道工事における管材費 | C7: 50535000 | E7: 15835000 | G7: 16660000 | I7: 特殊集計 区分(処分) | J7: =C8-E8 -> 255060 | K7: 51360000 | M7: 16660000 | O7: 34700000 | Q7: 42935000 | S7: 34700000 | U7: =C7-E7 -> 34700000 | V7: =IF(U7=O7,"OK","NG") -> OK
B8: ②直接工事費内の処分費等 | C8: 5772498 | E8: 5517438 | G8: 5526273 | I8: 特殊集計区分（水道） ＝水道工事における管財費 特殊集計区分（処分） ＝直工内の処分費等 | K8: 5781333 | M8: 5526273 | O8: 0 | Q8: 5772498 | S8: 0
B9: ③直接工事費内の処分費等の内、共通仮設費率分算出の対象外費 （共通仮設費対象額の３％を超える金額は率計算の対象としない） | C9: 1736124 | E9: 2721106 | G9: 2653370 | K9: 1668388 | M9: 2653370 | O9: 0 | Q9: 1850124 | S9: 0
A10: 共通仮設費
B11: ④共通仮設費積上分-運搬費 | C11: 23400 | E11: 23400 | G11: 23400 | I11: =C11-E11 -> 0 | K11: 23400 | M11: 23400 | O11: 0 | Q11: 23400 | S11: 0 | U11: =C11-E11 -> 0 | V11: =IF(U11=O11,"OK","NG") -> OK
B12: ⑤共通仮設費積上分-技術管理費 | C12: 946532 | E12: 132900 | G12: 138200 | I12: =C12-E12 -> 813632 | K12: 951832 | M12: 138200 | O12: 813632 | Q12: 946532 | S12: 813632 | U12: =C12-E12 -> 813632 | V12: =IF(U12=O12,"OK","NG") -> OK
B13: ⑥共通仮設費対象額※①-③-①’/2 | C13: =C5-C9-C7/2 -> 132809684 | E13: 直接工事費 共通仮設費（積上分） のみ使用 | G13: 直接工事費 共通仮設費（積上分） のみ使用 | I13: 直接工事費 共通仮設費（積上分） のみ使用 | K13: =K5-K9-K7/2 -> 135429809 | M13: =M5-M9-M7/2 -> 93110092 | O13: =O5-O9-O7/2 -> 41334735 | Q13: =Q5-Q9-Q7/2 -> 128895684 | S13: =S5-S9-S7/2 -> 41334735
B14: ⑦共通仮設費率分 | C14: 0.1133 | D14: =ROUNDDOWN(C13*C14,-3) -> 15047000 | K14: 0.1129 | L14: =ROUNDDOWN(K13*K14,-3) -> 15290000 | M14: =K14 -> 0.1129 | N14: =ROUNDDOWN(M13*M14,-3) -> 10512000 | O14: =C14 -> 0.1133 | P14: =ROUNDDOWN(O13*O14,-3) -> 4683000 | Q14: 0.1141 | R14: =ROUNDDOWN(Q13*Q14,-3) -> 14706000 | S14: =Q14 -> 0.1141 | T14: =ROUNDDOWN(S13*S14,-3) -> 4716000
B15: ⑧共通仮設費【合計】※④+⑤+⑦ | C15: =C11+C12+D14 -> 16016932 | K15: =K11+K12+L14 -> 16265232 | M15: =M11+M12+N14 -> 10673600 | O15: =O11+O12+P14 -> 5496632 | Q15: =Q11+Q12+R14 -> 15675932 | S15: =S11+S12+T14 -> 5529632
B16: ⑨純工事費※①+⑧ | C16: =C5+C15 -> 175830240 | K16: =K5+K15 -> 179043429 | M16: =M5+M15 -> 114767062 | O16: =O5+O15 -> 64181367 | Q16: =Q5+Q15 -> 167889240 | S16: =S5+S15 -> 64214367
A17: 現場管理費
B18: ⑩現場管理費対象額※⑨-③-①’/2 | C18: =C16-C9-C7/2 -> 148826616 | K18: =K16-K9-K7/2 -> 151695041 | M18: =M16-M9-M7/2 -> 103783692 | O18: =O16-O9-O7/2 -> 46831367 | Q18: =Q16-Q9-Q7/2 -> 144571616 | S18: =S16-S9-S7/2 -> 46864367
B19: ⑪現場管理費率分 | C19: 0.3537 | D19: =ROUNDDOWN(C19*C18,-3) -> 52639000 | K19: 0.3531 | L19: =ROUNDDOWN(K19*K18,-3) -> 53563000 | M19: =K19 -> 0.3531 | N19: =ROUNDDOWN(M19*M18,-3) -> 36646000 | O19: =C19 -> 0.3537 | P19: =ROUNDDOWN(O19*O18,-3) -> 16564000 | Q19: 0.3549 | R19: =ROUNDDOWN(Q19*Q18,-3) -> 51308000 | S19: =Q19 -> 0.3549 | T19: =ROUNDDOWN(S19*S18,-3) -> 16632000
B20: ⑫現場管理費【合計】※⑪ | C20: =D19 -> 52639000 | K20: =L19 -> 53563000 | M20: =N19 -> 36646000 | O20: =P19 -> 16564000 | Q20: =R19 -> 51308000 | S20: =T19 -> 16632000
B21: ⑬工事原価※⑨+⑫ | C21: =C16+C20 -> 228469240 | K21: =K16+K20 -> 232606429 | M21: =M16+M20 -> 151413062 | O21: =O16+O20 -> 80745367 | Q21: =Q16+Q20 -> 219197240 | S21: =S16+S20 -> 80846367
A22: 一般管理費
B23: ⑭一般管理費対象額※⑬-③ | C23: =C21-C9 -> 226733116 | K23: =K21-K9 -> 230938041 | M23: =M21-M9 -> 148759692 | O23: =O21-O9-O12 -> 79931735 | Q23: =Q21-Q9 -> 217347116 | S23: =S21-S9 -> 80846367
B24: ⑮一般管理費率分 | C24: 0.1533 | D24: =C24*C23 -> 34758187 | K24: 0.1529 | L24: =K24*K23 -> 35310426 | M24: =K24 -> 0.1529 | N24: =M24*M23 -> 22745357 | O24: =C24 -> 0.1533 | P24: =O24*O23 -> 12253535 | Q24: 0.1542 | R24: =Q24*Q23 -> 33514925 | S24: =Q24 -> 0.1542 | T24: =S24*S23 -> 12466510
B25: ⑯契約保証費※当初設計時額で固定 | C25: 77899 | K25: =C25 -> 77899 | M25: =C25 -> 77899 | O25: =C25 -> 77899 | Q25: 77899 | S25: 77899
B26: ⑰一般管理費【合計】（端数整理前）※⑮+⑯ | C26: =D24+C25 -> 34836086 | K26: =L24+K25 -> 35388325 | M26: =N24+M25 -> 22823256 | O26: =P24+O25 -> 12331434 | Q26: =R24+Q25 -> 33592824 | S26: =T24+S25 -> 12544409
B27: ⑱工事価格（端数整理前）※⑬+⑰ | C27: =C21+C26 -> 2.6330533e+08 | K27: =K21+K26 -> 2.6799475e+08 | M27: =M21+M26 -> 1.7423632e+08 | O27: =O21+O26 -> 93076801 | Q27: =Q21+Q26 -> 2.5279006e+08 | S27: =S21+S26 -> 93390776
B28: ⑲端数整理 | C28: =C27-ROUNDDOWN(C27,-3) -> 325.6828 | K28: =K27-ROUNDDOWN(K27,-3) -> 754.4689 | M28: =M27-ROUNDDOWN(M27,-3) -> 317.9068 | O28: =O27-ROUNDDOWN(O27,-3) -> 800.9755 | Q28: =Q27-ROUNDDOWN(Q27,-3) -> 64.2872 | S28: =S27-ROUNDDOWN(S27,-3) -> 775.7914
B29: ⑳一般管理費【合計】（端数整理後） | C29: =C26-C28 -> 34835760 | K29: =K26-K28 -> 35387571 | M29: =M26-M28 -> 22822938 | O29: =O26-O28 -> 12330633 | Q29: =Q26-Q28 -> 33592760 | S29: =S26-S28 -> 12543633
B30: ㉑工事価格※⑬+⑳ | C30: =C29+C21 -> 263305000 | K30: =K29+K21 -> 267994000 | M30: =M29+M21 -> 174236000 | O30: =O29+O21 -> 93076000 | Q30: =Q29+Q21 -> 252790000 | S30: =S29+S21 -> 93390000
A31: 工事費
B32: ㉒スクラップ | C32: -3684000 | K32: -4012000 | M32: -4012000 | O32: 0 | Q32: -3684000 | S32: 0
B33: ㉑’工事価格（スクラップ込み） ※㉑+㉒ | C33: =C30+C32 -> 259621000 | K33: =K30+K32 -> 263982000 | M33: =M30+M32 -> 170224000 | O33: =O30+O32 -> 93076000 | Q33: =Q30+Q32 -> 249106000 | S33: =S30+S32 -> 93390000
B34: ㉓消費税相当額 | C34: =(C30+C32)*0.1 -> 25962100 | K34: =(K30+K32)*0.1 -> 26398200 | M34: =(M30+M32)*0.1 -> 17022400 | O34: =(O30+O32)*0.1 -> 9307600 | Q34: =(Q30+Q32)*0.1 -> 24910600 | S34: =(S30+S32)*0.1 -> 9339000
B35: ㉔工事費※㉑+㉒+㉓ | C35: =C30+C32+C34 -> 285583100 | K35: =K30+K32+K34 -> 290380200 | M35: =M30+M32+M34 -> 187246400 | O35: =O30+O32+O34 -> 102383600 | Q35: =Q30+Q32+Q34 -> 274016600 | S35: =S30+S32+S34 -> 102729000
D37: :【旧経費率】積算システム計算結果から引用 | L37: :【新経費率】 積算システム計算結果から引用 | N37: :【設計書(3)】の【新経費率】を 用いて経費を計算 | P37: :変更設計書の【旧経費率】を 用いて経費を計算 | R37: :変更設計書 新工種抜きの 【経費率】を積算システム計算結果から引用 | T37: :変更設計書 新工種抜きの 【経費率】を用いて経費を計算
D38: :契約保証費は当初積算時から変更しない | L38: :契約保証費は当初積算時から 変更しない | N38: :契約保証費は当初積算時から 変更しない | P38: :契約保証費は当初積算時から 変更しない | R38: :契約保証費は当初積算時から 変更しない | T38: :契約保証費は当初積算時から 変更しない
P40: :スライド調書（様式4-2号）に転記
